cs110/__init__.py
cs110/autograder.py
cs110-0.5.3.dist-info/AUTHORS
cs110-0.5.3.dist-info/METADATA
cs110-0.5.3.dist-info/WHEEL
cs110-0.5.3.dist-info/pbr.json
cs110-0.5.3.dist-info/top_level.txt
cs110-0.5.3.dist-info/RECORD
