Metadata-Version: 2.1
Name: cs110
Version: 0.5.3
Summary: simple grading tool that connects to a custom web backend
Author: Adrian de Freitas
Author-email: adrian.defreitas@afacademy.af.edu
License: Unlicense
Classifier: Development Status :: 4 - Beta
Classifier: Programming Language :: Python
License-File: AUTHORS
Requires-Dist: colorama
Requires-Dist: pythonGraph
Requires-Dist: requests
Requires-Dist: xdg
